{
    "filename": "1frame6081",
    "file": "1frame6081.jpg",
    "annotations": [
        [
            {
                "id": "9JshP5W0aV",
                "type": "rectanglelabels",
                "value": {
                    "x": 41.30314743235781,
                    "y": 5.49558390578999,
                    "width": 4.472667034787409,
                    "height": 5.49558390578999,
                    "rotation": 0,
                    "rectanglelabels": [
                        "Speler"
                    ]
                },
                "origin": "manual",
                "to_name": "image",
                "from_name": "rectlabels",
                "image_rotation": 0,
                "original_width": 1920,
                "original_height": 1080
            }
        ]
    ]
}